phylo_converge/__init__.py
phylo_converge/alignment.py
phylo_converge/phylogeny.py
phylo_converge/visualization.py
tests/__init__.py
tests/test_alignment.py
tests/test_phylogeny.py
tests/test_visualization.py
phylo_converge-0.1.1.dist-info/LICENSE
phylo_converge-0.1.1.dist-info/METADATA
phylo_converge-0.1.1.dist-info/WHEEL
phylo_converge-0.1.1.dist-info/entry_points.txt
phylo_converge-0.1.1.dist-info/top_level.txt
phylo_converge-0.1.1.dist-info/RECORD
